{"color":"903F86D0",
"groups":{
"has_bow":1,
"in_desert":1,
"is_metall":5},
"name":"orichalcum",
"block":{
	"inventory_image":"minerdream_orichalcum_block.png"
	},
"ingot":{
	"grind_time":28,
	"inventory_image":"minerdream_orichalcum_ingot.png"
},
"ore":{
	"wherein":["stone","desert_stone"],
	"crack":6,
	"inventory_image":"minerdream_orichalcum_ore.png",
	"clust_size":3,
	"num_ores":3,
	"scarcity":17,
	"y_max":-6500,
	"y_min":-31000
},
"lump":{
	"crack":6,
	"inventory_image":"minerdream_orichalcum_lump.png",
	"stack_max":99,
	"cooking_time":86,
	"grind_time":80
},
"dust":{
	"crack":4,
	"cooking_time":44,
	"inventory_image":"minerdream_orichalcum_dust.png"
},
"nugget":{
	"crack":6,
	"inventory_image":"minerdream_orichalcum_nugget.png",
	"stack_max":99,
	"cooking_time":44
},
"poorore":{
	"wherein":["stone","desert_stone"],
	"inventory_image":"minerdream_orichalcum_poorore.png",
	"crack":6,
	"clust_size":3,
	"num_ores":3,
	"scarcity":17,
	"y_max":-6250
},
"tier":8,
"tools":{"maxlevel":5,"tool_stick":"minerdream:expensivestick","use":80,
	"axe":{"choppy":[0.95,0.28,0.19],"fleshy":16},
	"spear":{"range":8,"fleshy":19,"snappy":[1.15,0.46,0.03]},
	"sword":{"fleshy":17,"snappy":[1,0.5,0.04]},
	"pick":{"cracky":[0.9,0.45,0.1,2.5,3.25,4.75],"fleshy":16,"crumbly":[0.45,0.18,0.1]}
},
"3d_armor":{"cracky":2,"crumbly":1,"heal":9,"use":150,"snappy":3,"level":2,"choppy":2,"tool_cotton":"steel_wire",
"boots":{"fleshy":17,"gravity":-0.1,"jump":0.1,"speed":0.13},
"chestplate":{"fleshy":17,"gravity":-0.1,"jump":0.1,"speed":0.13},
"helmet":{"fleshy":17,"gravity":-0.1,"jump":0.1,"speed":0.13},
"leggings":{"fleshy":17,"gravity":-0.1,"jump":0.1,"speed":0.13},
"shields":{"fleshy":17,"gravity":-0.1,"jump":0.1,"speed":0.13}
	}
}
